pensionpro/__init__.py
pensionpro/api.py
pensionpro/errors.py
python_pensionpro-0.7.dist-info/LICENSE
python_pensionpro-0.7.dist-info/METADATA
python_pensionpro-0.7.dist-info/WHEEL
python_pensionpro-0.7.dist-info/top_level.txt
python_pensionpro-0.7.dist-info/RECORD
