Metadata-Version: 2.1
Name: python-pensionpro
Version: 0.7
Summary: Python library for interacting with PensionPro API.
Home-page: UNKNOWN
Author: Aaron Harabedian
License: MIT
Platform: UNKNOWN
Requires-Python: >=3.6
Requires-Dist: requests
